skytemple_eventserver/__init__.py
skytemple_eventserver/event_handler.py
skytemple_eventserver/module.py
skytemple_eventserver/websocket_server.py
skytemple_eventserver-1.6.0.dist-info/LICENSE
skytemple_eventserver-1.6.0.dist-info/METADATA
skytemple_eventserver-1.6.0.dist-info/WHEEL
skytemple_eventserver-1.6.0.dist-info/entry_points.txt
skytemple_eventserver-1.6.0.dist-info/top_level.txt
skytemple_eventserver-1.6.0.dist-info/RECORD
