Metadata-Version: 2.1
Name: skytemple-eventserver
Version: 1.6.0
Summary: Websocket server that emits SkyTemple UI events
Home-page: https://github.com/SkyTemple/skytemple-eventserver/
Classifier: Development Status :: 4 - Beta
Classifier: Programming Language :: Python
Classifier: License :: OSI Approved :: GNU General Public License v3 or later (GPLv3+)
Classifier: Programming Language :: Python :: 3.8
Classifier: Programming Language :: Python :: 3.9
Classifier: Programming Language :: Python :: 3.10
Classifier: Programming Language :: Python :: 3.11
License-File: LICENSE
